{
  "name": "zeit-my-app",
  "alias": "zeit-my-app",
  "version": 2,
  "builds": [
    { "src": "date.js", "use": "@now/node" },
    { "src": "videos.js", "use": "@now/node" },
    { "src": "graphql.js", "use": "@now/node" },
    { "src": "index.html", "use": "@now/static" },
    { "src": "assets/images/avatar.png", "use": "@now/static" },
    { "src": "cowsay.py", "use": "@now/python" }
  ],
  "env": {
    "MY_NAME": "Volcy, Clervens",
    "MY_EMAIL": "@email",
    "MONGODB_URI": "@mongodb_uri"
  }
}